CHANGES.rst
CONTRIBUTORS.rst
MANIFEST.in
README.rst
bootstrap.py
buildout.cfg
setup.py
test-4.0.x.cfg
test-4.1.x.cfg
test-4.2.x.cfg
docs/LICENSE.GPL
docs/LICENSE.txt
src/collective/__init__.py
src/collective.error.detector.egg-info/PKG-INFO
src/collective.error.detector.egg-info/SOURCES.txt
src/collective.error.detector.egg-info/dependency_links.txt
src/collective.error.detector.egg-info/entry_points.txt
src/collective.error.detector.egg-info/namespace_packages.txt
src/collective.error.detector.egg-info/not-zip-safe
src/collective.error.detector.egg-info/requires.txt
src/collective.error.detector.egg-info/top_level.txt
src/collective/error/__init__.py
src/collective/error/detector/__init__.py
src/collective/error/detector/config.py
src/collective/error/detector/configure.zcml
src/collective/error/detector/handlers.py
src/collective/error/detector/interfaces.py
src/collective/error/detector/memoize.py
src/collective/error/detector/requestutils.py
src/collective/error/detector/testing.py
src/collective/error/detector/testing.zcml
src/collective/error/detector/profiles/default/browserlayer.xml
src/collective/error/detector/profiles/default/metadata.xml
src/collective/error/detector/profiles/testing/metadata.xml
src/collective/error/detector/tests/__init__.py
src/collective/error/detector/tests/test_logger.py
src/collective/error/detector/tests/test_setup.py